odoo/addons/purchase_analytic_global/README.rst
odoo/addons/purchase_analytic_global/__init__.py
odoo/addons/purchase_analytic_global/__manifest__.py
odoo/addons/purchase_analytic_global/i18n/fr.po
odoo/addons/purchase_analytic_global/i18n/purchase_analytic_global.pot
odoo/addons/purchase_analytic_global/models/__init__.py
odoo/addons/purchase_analytic_global/models/purchase.py
odoo/addons/purchase_analytic_global/readme/CONTRIBUTORS.rst
odoo/addons/purchase_analytic_global/readme/DESCRIPTION.rst
odoo/addons/purchase_analytic_global/static/description/icon.png
odoo/addons/purchase_analytic_global/static/description/index.html
odoo/addons/purchase_analytic_global/views/purchase.xml
odoo12_addon_purchase_analytic_global-12.0.1.0.0.99.dev3.dist-info/METADATA
odoo12_addon_purchase_analytic_global-12.0.1.0.0.99.dev3.dist-info/WHEEL
odoo12_addon_purchase_analytic_global-12.0.1.0.0.99.dev3.dist-info/top_level.txt
odoo12_addon_purchase_analytic_global-12.0.1.0.0.99.dev3.dist-info/RECORD
